[
	{
		"__TYPE__": "SharedSliceContent",
		"variation": "default",
		"primary": {
			"title": {
				"__TYPE__": "StructuredTextContent",
				"value": [
					{
						"type": "heading2",
						"content": {
							"text": "Kitchen"
						}
					}
				]
			}
		},
		"items": [
			{
				"__TYPE__": "GroupItemContent",
				"value": [
					[
						"title",
						{
							"__TYPE__": "StructuredTextContent",
							"value": [
								{
									"type": "heading4",
									"content": {
										"text": "Might"
									}
								}
							]
						}
					],
					[
						"text",
						{
							"__TYPE__": "StructuredTextContent",
							"value": [
								{
									"type": "paragraph",
									"content": {
										"text": "Consectetur aliquip nulla laborum aliquip minim. Ex amet et exercitation cupidatat consequat do ad dolore laboris nisi."
									}
								}
							]
						}
					]
				]
			}
		]
	}
]